cpan123/Auth.py
cpan123/Directlink.py
cpan123/Downloader.py
cpan123/File.py
cpan123/File2.py
cpan123/FileList.py
cpan123/Offline.py
cpan123/Share.py
cpan123/Uploader.py
cpan123/User.py
cpan123/__init__.py
cpan123/authtype/Jwt.py
cpan123/authtype/OAuth.py
cpan123/authtype/__init__.py
cpan123/cli.py
cpan123/model/Base.py
cpan123/model/encode.py
cpan123/utils/Constants.py
cpan123/utils/EnvConfig.py
cpan123/utils/Logger.py
cpan123/utils/__init__.py
cpan123/utils/md5.py
cpan123-0.2.9.dist-info/WHEEL
cpan123-0.2.9.dist-info/entry_points.txt
cpan123-0.2.9.dist-info/METADATA
cpan123-0.2.9.dist-info/RECORD
